{
	"name": "01_PL_VENU_IDL_WM",
	"properties": {
		"activities": [
			{
				"name": "Lookup_oldWM",
				"type": "Lookup",
				"dependsOn": [],
				"policy": {
					"timeout": "0.12:00:00",
					"retry": 0,
					"retryIntervalInSeconds": 30,
					"secureOutput": false,
					"secureInput": false
				},
				"userProperties": [],
				"typeProperties": {
					"source": {
						"type": "AzureSqlSource",
						"queryTimeout": "02:00:00",
						"partitionOption": "None"
					},
					"dataset": {
						"referenceName": "DS_SQL_VENU_SRC_WMTABLE",
						"type": "DatasetReference"
					},
					"firstRowOnly": false
				}
			},
			{
				"name": "Lookup_newWM",
				"type": "Lookup",
				"dependsOn": [],
				"policy": {
					"timeout": "0.12:00:00",
					"retry": 0,
					"retryIntervalInSeconds": 30,
					"secureOutput": false,
					"secureInput": false
				},
				"userProperties": [],
				"typeProperties": {
					"source": {
						"type": "AzureSqlSource",
						"sqlReaderQuery": "select MAX(LastModifytime) as NewWatermarkvalue from dst_venu",
						"queryTimeout": "02:00:00",
						"partitionOption": "None"
					},
					"dataset": {
						"referenceName": "DS_SQL_VENU_DSTable",
						"type": "DatasetReference"
					},
					"firstRowOnly": false
				}
			},
			{
				"name": "Copy data1",
				"type": "Copy",
				"dependsOn": [
					{
						"activity": "Lookup_oldWM",
						"dependencyConditions": [
							"Succeeded"
						]
					},
					{
						"activity": "Lookup_newWM",
						"dependencyConditions": [
							"Succeeded"
						]
					}
				],
				"policy": {
					"timeout": "0.12:00:00",
					"retry": 0,
					"retryIntervalInSeconds": 30,
					"secureOutput": false,
					"secureInput": false
				},
				"userProperties": [],
				"typeProperties": {
					"source": {
						"type": "AzureSqlSource",
						"sqlReaderQuery": {
							"value": "select * from dst_venu where LastModifytime > '@{activity('Lookup_oldWM').output.value[0].WatermarkValue}' and \nLastModifytime <=' @{activity('Lookup_newWM').output.value[0].NewWatermarkvalue}'\n",
							"type": "Expression"
						},
						"queryTimeout": "02:00:00",
						"partitionOption": "None"
					},
					"sink": {
						"type": "DelimitedTextSink",
						"storeSettings": {
							"type": "AzureBlobFSWriteSettings"
						},
						"formatSettings": {
							"type": "DelimitedTextWriteSettings",
							"quoteAllText": true,
							"fileExtension": ".txt"
						}
					},
					"enableStaging": false,
					"translator": {
						"type": "TabularTranslator",
						"typeConversion": true,
						"typeConversionSettings": {
							"allowDataTruncation": true,
							"treatBooleanAsNumber": false
						}
					}
				},
				"inputs": [
					{
						"referenceName": "DS_SQL_VENU_SRC_WMTABLE",
						"type": "DatasetReference"
					}
				],
				"outputs": [
					{
						"referenceName": "ds_venu_gen2",
						"type": "DatasetReference"
					}
				]
			},
			{
				"name": "Stored procedure1",
				"type": "SqlServerStoredProcedure",
				"dependsOn": [
					{
						"activity": "Copy data1",
						"dependencyConditions": [
							"Succeeded"
						]
					}
				],
				"policy": {
					"timeout": "0.12:00:00",
					"retry": 0,
					"retryIntervalInSeconds": 30,
					"secureOutput": false,
					"secureInput": false
				},
				"userProperties": [],
				"typeProperties": {
					"storedProcedureName": "[dbo].[usp_write_wm_venu]",
					"storedProcedureParameters": {
						"LastModifiedtime": {
							"value": {
								"value": "@activity('Lookup_newWM').output.value[0].NewWatermarkvalue",
								"type": "Expression"
							},
							"type": "DateTime"
						},
						"TableName": {
							"value": {
								"value": "@activity('Lookup_oldWM').output.value[0].TableName",
								"type": "Expression"
							},
							"type": "String"
						}
					}
				},
				"linkedServiceName": {
					"referenceName": "LS_SQL_VENU_WM",
					"type": "LinkedServiceReference"
				}
			}
		],
		"annotations": []
	}
}